[{"model": "catalog.category", "pk": 40, "fields": {"name": "Классическая зарубежная проза", "description": null}}, {"model": "catalog.category", "pk": 41, "fields": {"name": "Исторический детектив", "description": null}}, {"model": "catalog.category", "pk": 42, "fields": {"name": "Классическая отечественная проза", "description": null}}, {"model": "catalog.category", "pk": 43, "fields": {"name": "Личная эффективность, мотивация", "description": null}}, {"model": "catalog.product", "pk": 45, "fields": {"name": "Повелитель мух", "description": "Если лицо совершенно меняется от того, сверху или снизу его осветить, — чего же стоит лицо? И чего же всё вообще тогда стоит?", "image": "products/1664290389_4-damion-club-p-povelitel-mukh-art-instagram-4_XvKRTJM.png", "category": 40, "purchase_price": 276, "date_creation": "2023-08-03T00:14:21.944Z", "date_last_modification": "2023-08-03T00:45:17.143Z"}}, {"model": "catalog.product", "pk": 46, "fields": {"name": "Десять негритят", "description": "У сумасшедшего уйма преимуществ перед нормальными людьми. Они вдвое хитрее.", "image": "products/6013249955_SZejYCA.jpg", "category": 41, "purchase_price": 299, "date_creation": "2023-08-03T00:14:21.944Z", "date_last_modification": "2023-08-03T00:45:01.893Z"}}, {"model": "catalog.product", "pk": 47, "fields": {"name": "Идиот", "description": "Я пришел вас предупредить: во-первых, мне денег взаймы не давать, потому что я непременно буду просить.", "image": "products/uk970318_zMh4mZ2.jpg", "category": 42, "purchase_price": 329, "date_creation": "2023-08-03T00:14:21.944Z", "date_last_modification": "2023-08-03T00:45:09.062Z"}}, {"model": "catalog.product", "pk": 48, "fields": {"name": "48 законов", "description": "Мудрец получит больше пользы от своих врагов, чем глупец от своих друзей.", "image": "products/6488843392_xCyK0Hf.jpg", "category": 43, "purchase_price": 479, "date_creation": "2023-08-03T00:14:21.944Z", "date_last_modification": "2023-08-03T00:44:40.132Z"}}, {"model": "catalog.product", "pk": 55, "fields": {"name": "451° по Фаренгейту", "description": "Есть преступления хуже, чем сжигать книги. Например — не читать их.", "image": "products/249461.970_WEtKtfv.jpg", "category": 40, "purchase_price": 339, "date_creation": "2023-08-08T20:08:30.886Z", "date_last_modification": "2023-08-08T20:08:30.886Z"}}]